aiida_atoms/__init__.py
aiida_atoms/tracker.py
aiida_atoms/transformations.py
aiida_atoms-0.1.0.dist-info/LICENSE
aiida_atoms-0.1.0.dist-info/WHEEL
aiida_atoms-0.1.0.dist-info/METADATA
aiida_atoms-0.1.0.dist-info/RECORD
