Metadata-Version: 2.1
Name: aiida-atoms
Version: 0.1.0
Summary: AiiDA demo plugin that wraps the `diff` executable for computing the difference between two files.
Keywords: aiida,plugin
Author-email: Bonan Zhu <zhubonan@outlook.com>
Requires-Python: >=3.7
Classifier: Programming Language :: Python
Classifier: Intended Audience :: Science/Research
Classifier: License :: OSI Approved :: MIT License
Classifier: Natural Language :: English
Classifier: Development Status :: 3 - Alpha
Classifier: Framework :: AiiDA
Requires-Dist: aiida-core>=2.0,<3
Requires-Dist: ase>=3,<4
Requires-Dist: numpy
Requires-Dist: sphinx ; extra == "docs"
Requires-Dist: jupytext ; extra == "docs"
Requires-Dist: sphinx-autodoc2 ; extra == "docs"
Requires-Dist: sphinx-copybutton ; extra == "docs"
Requires-Dist: myst-nb ; extra == "docs"
Requires-Dist: linkify-it-py ; extra == "docs"
Requires-Dist: sphinx-autobuild ; extra == "docs"
Requires-Dist: sphinx-book-theme ; extra == "docs"
Requires-Dist: sphinxcontrib-contentui ; extra == "docs"
Requires-Dist: sphinxcontrib-details-directive ; extra == "docs"
Requires-Dist: markupsafe<2.1 ; extra == "docs"
Requires-Dist: pre-commit~=2.2 ; extra == "pre-commit"
Requires-Dist: pylint~=2.15.10 ; extra == "pre-commit"
Requires-Dist: pgtest~=1.3.1 ; extra == "testing"
Requires-Dist: wheel~=0.31 ; extra == "testing"
Requires-Dist: coverage[toml] ; extra == "testing"
Requires-Dist: pytest~=6.0 ; extra == "testing"
Requires-Dist: pytest-cov ; extra == "testing"
Project-URL: Source, https://github.com/zhubonan/aiida-atoms
Provides-Extra: docs
Provides-Extra: pre-commit
Provides-Extra: testing
